{"16569825": {"sku": "AQALDFLAA0-NLG-LCE", "lowest_price": 179.92, "image": "", "status": "Neaktyvus", "store_id": "", "url": "", "price": "", "currency": "", "sizes": {}}, "16267407": {"sku": "AQCELHIGS0-GRO-989", "lowest_price": 370.34, "image": "", "status": "Neaktyvus", "store_id": "", "url": "", "price": "", "currency": "", "sizes": {}}, "14544821": {"sku": "AQDENFLAB0-SUE-000", "lowest_price": 182.30433, "image": "", "status": "Nenurodyta FF faile", "store_id": "", "url": "", "price": "", "currency": "", "sizes": {}}, "14002231": {"sku": "AQDENHIGP0-SUE-000", "lowest_price": 204.81111, "image": "", "status": "Nenurodyta FF faile", "store_id": "", "url": "", "price": "", "currency": "", "sizes": {}}, "15509404": {"sku": "AQDENHIGP0-SUE-ECA", "lowest_price": 202.6665, "image": "", "status": "Nenurodyta FF faile", "store_id": "", "url": "", "price": "", "currency": "", "sizes": {}}, "14544355": {"sku": "AQDENHIGS0-SUE-000", "lowest_price": 205.18435, "image": "", "status": "Nenurodyta FF faile", "store_id": "", "url": "", "price": "", "currency": "", "sizes": {}}, "15335688": {"sku": "AQDENHIGS0-SUE-ECA", "lowest_price": 205.48375, "image": "", "status": "Neaktyvus", "store_id": "", "url": "", "price": "", "currency": "", "sizes": {}}, "13085027": {"sku": "AQDENMIDP0-SUE-000", "lowest_price": 201.58067, "image": "", "status": "Nenurodyta FF faile", "store_id": "", "url": "", "price": "", "currency": "", "sizes": {}}, "16277153": {"sku": "AQMDTMIDS0-NAP-NND", "lowest_price": 295.06833, "image": "", "status": "Neaktyvus", "store_id": "", "url": "", "price": "", "currency": "", "sizes": {}}, "15458580": {"sku": "AQPURHIGP1-NAP-ECA", "lowest_price": 181.76571, "image": "", "status": "Nenurodyta FF faile", "store_id": "", "url": "", "price": "", "currency": "", "sizes": {}}, "14857937": {"sku": "AQSNUHIGS0-NAP-PWP", "lowest_price": 183.66429, "image": "", "status": "Nenurodyta FF faile", "store_id": "", "url": "", "price": "", "currency": "", "sizes": {}}, "13855597": {"sku": "AQSNUHIGS0-SUE-000", "lowest_price": 183.80952, "image": "", "status": "Nenurodyta FF faile", "store_id": "", "url": "", "price": "", "currency": "", "sizes": {}}, "15592172": {"sku": "AQSNUMIDS0-NAP-PWP", "lowest_price": "", "image": "", "status": "Nenurodyta FF faile", "store_id": "", "url": "", "price": "", "currency": "", "sizes": {}}, "15181848": {"sku": "AQSNUMIDS0-SUE-000", "lowest_price": 183.66333, "image": "", "status": "Nenurodyta FF faile", "store_id": "", "url": "", "price": "", "currency": "", "sizes": {}}, "16624895": {"sku": "AQSOLFLAS0-SUN-COF", "lowest_price": 187.07143, "image": "", "status": "Neaktyvus", "store_id": "", "url": "", "price": "", "currency": "", "sizes": {}}, "16179491": {"sku": "AQTWIHIGS0-NAP-NND", "lowest_price": "", "image": "", "status": "Neaktyvus", "store_id": "", "url": "", "price": "", "currency": "", "sizes": {}}, "16523135": {"sku": "AQVLTHIGL0-SUE-000", "lowest_price": 183.666, "image": "", "status": "Neaktyvus", "store_id": "", "url": "", "price": "", "currency": "", "sizes": {}}, "16523136": {"sku": "AQVLTHIGL0-SUE-NND", "lowest_price": 184.1, "image": "", "status": "Neaktyvus", "store_id": "", "url": "", "price": "", "currency": "", "sizes": {}}, "16448437": {"sku": "BAL163715P13Z2GLOSBI", "lowest_price": 134.93, "image": "", "status": "Nenurodyta FF faile", "store_id": "", "url": "", "price": "", "currency": "", "sizes": {}}, "16448434": {"sku": "BAL166200P11Z2NAPI00", "lowest_price": 148.1675, "image": "", "status": "Neaktyvus", "store_id": "", "url": "", "price": "", "currency": "", "sizes": {}}, "16448435": {"sku": "BAL166200P11Z2NAPI78", "lowest_price": 149.7725, "image": "", "status": "Neaktyvus", "store_id": "", "url": "", "price": "", "currency": "", "sizes": {}}, "16448439": {"sku": "BAL167600P13Z2VICONE", "lowest_price": 135.625, "image": "", "status": "Nenurodyta FF faile", "store_id": "", "url": "", "price": "", "currency": "", "sizes": {}}, "16448436": {"sku": "BAL196302XVITE000000", "lowest_price": 148.85, "image": "https://cdn-images.farfetch-contents.com/16/44/84/36/16448436_32526974_480.jpg", "status": "Aktyvus", "store_id": 10136, "url": "https://www.farfetch.com//de/shopping/men/baldinini-klassische-sneakers-item-16448436.aspx?storeid=10136", "price": 308, "currency": "EUR", "sizes": {}, "country_id": ""}, "16447403": {"sku": "BAL196304XVITE000000", "lowest_price": 153.277, "image": "https://cdn-images.farfetch-contents.com/16/44/74/03/16447403_32771447_480.jpg", "status": "Aktyvus", "store_id": 10136, "url": "https://www.farfetch.com//de/shopping/men/baldinini-sneakers-aus-leder-item-16447403.aspx?storeid=10136", "price": 318, "currency": "EUR", "sizes": {}, "country_id": ""}, "16448440": {"sku": "BAL196309XCOCC909090", "lowest_price": 154.93667, "image": "https://cdn-images.farfetch-contents.com/16/44/84/40/16448440_33295460_480.jpg", "status": "Aktyvus", "store_id": 10136, "url": "https://www.farfetch.com//de/shopping/men/baldinini-sneakers-mit-kroko-pragung-item-16448440.aspx?storeid=10136", "price": 318, "currency": "EUR", "sizes": {}, "country_id": ""}, "16447402": {"sku": "BAL196315XVITE909090", "lowest_price": 153.96444, "image": "https://cdn-images.farfetch-contents.com/16/44/74/02/16447402_32643611_480.jpg", "status": "Aktyvus", "store_id": 10136, "url": "https://www.farfetch.com//de/shopping/men/baldinini-scarpa-uomo-vitello-sneakers-item-16447402.aspx?storeid=10136", "price": 318, "currency": "EUR", "sizes": {}, "country_id": ""}, "16448438": {"sku": "BAL196321XVITE101010", "lowest_price": 152.26545, "image": "https://cdn-images.farfetch-contents.com/16/44/84/38/16448438_32039755_480.jpg", "status": "Aktyvus", "store_id": 10136, "url": "https://www.farfetch.com//de/shopping/men/baldinini-sneakers-mit-perforiertem-detail-item-16448438.aspx?storeid=10136", "price": 318, "currency": "EUR", "sizes": {}, "country_id": ""}, "16448441": {"sku": "BAL196334XWISA0000XX", "lowest_price": 160.63333, "image": "https://cdn-images.farfetch-contents.com/16/44/84/41/16448441_32036533_480.jpg", "status": "Aktyvus", "store_id": 10136, "url": "https://www.farfetch.com//de/shopping/men/baldinini-sneakers-mit-logo-schild-item-16448441.aspx?storeid=10136", "price": 329, "currency": "EUR", "sizes": {}, "country_id": ""}, "16447401": {"sku": "BAL196510XMOUS000000", "lowest_price": 126.888, "image": "https://cdn-images.farfetch-contents.com/16/44/74/01/16447401_32166131_480.jpg", "status": "Aktyvus", "store_id": 10136, "url": "https://www.farfetch.com//de/shopping/men/baldinini-pantoletten-mit-logo-pragung-item-16447401.aspx?storeid=10136", "price": 265, "currency": "EUR", "sizes": {}, "country_id": ""}, "16448445": {"sku": "BAL196510XMOUS101010", "lowest_price": 126.888, "image": "https://cdn-images.farfetch-contents.com/16/44/84/45/16448445_32041238_480.jpg", "status": "Aktyvus", "store_id": 10136, "url": "https://www.farfetch.com//de/shopping/men/baldinini-sandalen-mit-uberkreuzten-riemen-item-16448445.aspx?storeid=10136", "price": 265, "currency": "EUR", "sizes": {}, "country_id": ""}, "16448451": {"sku": "BAL196520XVITE000000", "lowest_price": 126.8875, "image": "https://cdn-images.farfetch-contents.com/16/44/84/51/16448451_32040922_480.jpg", "status": "Aktyvus", "store_id": 10136, "url": "https://www.farfetch.com//de/shopping/men/baldinini-sandalen-mit-uberkreuzten-riemen-item-16448451.aspx?storeid=10136", "price": 265, "currency": "EUR", "sizes": {}, "country_id": ""}, "16448442": {"sku": "BAL196522XVITE000000", "lowest_price": 131.96313, "image": "https://cdn-images.farfetch-contents.com/16/44/84/42/16448442_32037141_480.jpg", "status": "Aktyvus", "store_id": 10136, "url": "https://www.farfetch.com//de/shopping/men/baldinini-sandalen-mit-uberkreuzten-riemen-item-16448442.aspx?storeid=10136", "price": 276, "currency": "EUR", "sizes": {}, "country_id": ""}, "16448443": {"sku": "BAL196729XCAPR000000", "lowest_price": 165.07706, "image": "https://cdn-images.farfetch-contents.com/16/44/84/43/16448443_32770610_480.jpg", "status": "Aktyvus", "store_id": 10136, "url": "https://www.farfetch.com//de/shopping/men/baldinini-klassische-schnurschuhe-item-16448443.aspx?storeid=10136", "price": 340, "currency": "EUR", "sizes": {}, "country_id": ""}, "16448453": {"sku": "BAL197037XLOSA101010", "lowest_price": 162.89375, "image": "https://cdn-images.farfetch-contents.com/16/44/84/53/16448453_32686644_480.jpg", "status": "Aktyvus", "store_id": 10136, "url": "https://www.farfetch.com//de/shopping/men/baldinini-loafer-mit-perforiertem-detail-item-16448453.aspx?storeid=10136", "price": 340, "currency": "EUR", "sizes": {}, "country_id": ""}, "16447404": {"sku": "BAL197062XLOTI1010XX", "lowest_price": 162.892, "image": "https://cdn-images.farfetch-contents.com/16/44/74/04/16447404_32688101_480.jpg", "status": "Aktyvus", "store_id": 10136, "url": "https://www.farfetch.com//de/shopping/men/baldinini-loafer-mit-perforiertem-detail-item-16447404.aspx?storeid=10136", "price": 340, "currency": "EUR", "sizes": {}, "country_id": ""}, "16448446": {"sku": "BAL197072XVINT101010", "lowest_price": 189.9125, "image": "https://cdn-images.farfetch-contents.com/16/44/84/46/16448446_32773569_480.jpg", "status": "Aktyvus", "store_id": 10136, "url": "https://www.farfetch.com//de/shopping/men/baldinini-budapester-mit-webmuster-item-16448446.aspx?storeid=10136", "price": 393, "currency": "EUR", "sizes": {}, "country_id": ""}, "16448444": {"sku": "BAL197072XVINT404040", "lowest_price": 188.3464, "image": "https://cdn-images.farfetch-contents.com/16/44/84/44/16448444_32686891_480.jpg", "status": "Aktyvus", "store_id": 10136, "url": "https://www.farfetch.com//de/shopping/men/baldinini-budapester-mit-webmuster-item-16448444.aspx?storeid=10136", "price": 393, "currency": "EUR", "sizes": {}, "country_id": ""}, "16447405": {"sku": "BAL197100XENGL101010", "lowest_price": 164.24875, "image": "https://cdn-images.farfetch-contents.com/16/44/74/05/16447405_32775094_480.jpg", "status": "Aktyvus", "store_id": 10136, "url": "https://www.farfetch.com//de/shopping/men/baldinini-budapester-mit-schnurung-item-16447405.aspx?storeid=10136", "price": 340, "currency": "EUR", "sizes": {}, "country_id": ""}, "16447406": {"sku": "BAL197418YDADV1010XX", "lowest_price": 157.342, "image": "https://cdn-images.farfetch-contents.com/16/44/74/06/16447406_32035287_480.jpg", "status": "Aktyvus", "store_id": 10136, "url": "https://www.farfetch.com//de/shopping/men/baldinini-loafer-mit-logo-schild-item-16447406.aspx?storeid=10136", "price": 329, "currency": "EUR", "sizes": {}, "country_id": ""}, "16448449": {"sku": "BAL197423YNABU101010", "lowest_price": 191.72083, "image": "https://cdn-images.farfetch-contents.com/16/44/84/49/16448449_32042146_480.jpg", "status": "Aktyvus", "store_id": 10136, "url": "https://www.farfetch.com//de/shopping/men/baldinini-espadrilles-mit-logo-schild-item-16448449.aspx?storeid=10136", "price": 393, "currency": "EUR", "sizes": {}, "country_id": ""}, "16447408": {"sku": "BAL197430YDAIN000000", "lowest_price": 160.13, "image": "https://cdn-images.farfetch-contents.com/16/44/74/08/16447408_32493674_480.jpg", "status": "Aktyvus", "store_id": 10136, "url": "https://www.farfetch.com//de/shopping/men/baldinini-perforierte-loafer-mit-logo-schild-item-16447408.aspx?storeid=10136", "price": 329, "currency": "EUR", "sizes": {}, "country_id": ""}, "16447411": {"sku": "BAL197430YDAIN101010", "lowest_price": 157.83353, "image": "https://cdn-images.farfetch-contents.com/16/44/74/11/16447411_32770705_480.jpg", "status": "Aktyvus", "store_id": 10136, "url": "https://www.farfetch.com//de/shopping/men/baldinini-loafer-mit-logo-schild-item-16447411.aspx?storeid=10136", "price": 329, "currency": "EUR", "sizes": {}, "country_id": ""}, "16448447": {"sku": "BAL197432YDAIN000000", "lowest_price": 157.34, "image": "https://cdn-images.farfetch-contents.com/16/44/84/47/16448447_32039744_480.jpg", "status": "Aktyvus", "store_id": 10136, "url": "https://www.farfetch.com//de/shopping/men/baldinini-loafer-mit-stegverzierung-item-16448447.aspx?storeid=10136", "price": 329, "currency": "EUR", "sizes": {}, "country_id": ""}, "16447407": {"sku": "BAL197800XVITE000000", "lowest_price": 91.36, "image": "https://cdn-images.farfetch-contents.com/16/44/74/07/16447407_32041132_480.jpg", "status": "Aktyvus", "store_id": 10136, "url": "https://www.farfetch.com//de/shopping/men/baldinini-sandalen-mit-uberkreuzten-riemen-item-16447407.aspx?storeid=10136", "price": 191, "currency": "EUR", "sizes": {}, "country_id": ""}, "16448448": {"sku": "BAL198026XVILA9086XX", "lowest_price": 191.76, "image": "", "status": "Neaktyvus", "store_id": "", "url": "", "price": "", "currency": "", "sizes": {}}, "16448452": {"sku": "BAL198306XNAPP000000", "lowest_price": 131.965, "image": "", "status": "Neaktyvus", "store_id": "", "url": "", "price": "", "currency": "", "sizes": {}}, "16447409": {"sku": "BAL199010XVISP9086XX", "lowest_price": 160.10125, "image": "", "status": "Neaktyvus", "store_id": "", "url": "", "price": "", "currency": "", "sizes": {}}, "16447410": {"sku": "BAL199012XVISP0086XX", "lowest_price": 143.0587, "image": "", "status": "Neaktyvus", "store_id": "", "url": "", "price": "", "currency": "", "sizes": {}}, "16448450": {"sku": "BAL199015XVITE000000", "lowest_price": 144.6075, "image": "", "status": "Neaktyvus", "store_id": "", "url": "", "price": "", "currency": "", "sizes": {}}, "12056166": {"sku": "BIR1005292", "lowest_price": "", "image": "", "status": "Nenurodyta FF faile", "store_id": "", "url": "", "price": "", "currency": "", "sizes": {}}, "15288680": {"sku": "BIR1005294_211", "lowest_price": "", "image": "", "status": "Nenurodyta FF faile", "store_id": "", "url": "", "price": "", "currency": "", "sizes": {}}, "12056167": {"sku": "BIR1005961_211", "lowest_price": "", "image": "", "status": "Nenurodyta FF faile", "store_id": "", "url": "", "price": "", "currency": "", "sizes": {}}, "15302129": {"sku": "BIR1012283", "lowest_price": "", "image": "", "status": "Nenurodyta FF faile", "store_id": "", "url": "", "price": "", "currency": "", "sizes": {}}, "15201863": {"sku": "BIR1015892", "lowest_price": "", "image": "", "status": "Nenurodyta FF faile", "store_id": "", "url": "", "price": "", "currency": "", "sizes": {}}, "16078237": {"sku": "BIR1016028", "lowest_price": "", "image": "", "status": "Nenurodyta FF faile", "store_id": "", "url": "", "price": "", "currency": "", "sizes": {}}, "15131472": {"sku": "BIR1016109_211", "lowest_price": "", "image": "", "status": "Nenurodyta FF faile", "store_id": "", "url": "", "price": "", "currency": "", "sizes": {}}, "16076377": {"sku": "BIR1016110", "lowest_price": "", "image": "", "status": "Nenurodyta FF faile", "store_id": "", "url": "", "price": "", "currency": "", "sizes": {}}, "14960717": {"sku": "BIR1016111_211", "lowest_price": "", "image": "", "status": "Nenurodyta FF faile", "store_id": "", "url": "", "price": "", "currency": "", "sizes": {}}, "16076392": {"sku": "BIR1016214", "lowest_price": "", "image": "", "status": "Nenurodyta FF faile", "store_id": "", "url": "", "price": "", "currency": "", "sizes": {}}, "16078236": {"sku": "BIR1016215", "lowest_price": "", "image": "", "status": "Nenurodyta FF faile", "store_id": "", "url": "", "price": "", "currency": "", "sizes": {}}, "16077387": {"sku": "BIR1016834", "lowest_price": "", "image": "", "status": "Nenurodyta FF faile", "store_id": "", "url": "", "price": "", "currency": "", "sizes": {}}, "16078229": {"sku": "BIR1016868", "lowest_price": "", "image": "", "status": "Nenurodyta FF faile", "store_id": "", "url": "", "price": "", "currency": "", "sizes": {}}, "16522849": {"sku": "BIR1016950", "lowest_price": "", "image": "", "status": "Nenurodyta FF faile", "store_id": "", "url": "", "price": "", "currency": "", "sizes": {}}, "16431021": {"sku": "BIR1017416", "lowest_price": "", "image": "", "status": "Nenurodyta FF faile", "store_id": "", "url": "", "price": "", "currency": "", "sizes": {}}, "16524369": {"sku": "BIR1018785", "lowest_price": "", "image": "", "status": "Nenurodyta FF faile", "store_id": "", "url": "", "price": "", "currency": "", "sizes": {}}, "16233533": {"sku": "BIR1019374", "lowest_price": "", "image": "", "status": "Nenurodyta FF faile", "store_id": "", "url": "", "price": "", "currency": "", "sizes": {}}, "13715822": {"sku": "BIR129443_211", "lowest_price": "", "image": "", "status": "Nenurodyta FF faile", "store_id": "", "url": "", "price": "", "currency": "", "sizes": {}}, "15131298": {"sku": "BIR34193", "lowest_price": "", "image": "https://cdn-images.farfetch-contents.com/15/13/12/98/15131298_25902387_480.jpg", "status": "Aktyvus", "store_id": 11719, "url": "https://www.farfetch.com//de/shopping/men/birkenstock-milano-sandalen-item-15131298.aspx?storeid=11719", "price": 113, "currency": "EUR", "sizes": {}, "country_id": ""}, "16522768": {"sku": "BIR34703", "lowest_price": "", "image": "https://cdn-images.farfetch-contents.com/16/52/27/68/16522768_32193972_480.jpg", "status": "Konkurentu", "store_id": 9885, "url": "https://www.farfetch.com//de/shopping/men/birkenstock-milano-sandalen-mit-doppelschnalle-item-16522768.aspx?storeid=9885", "price": 86, "currency": "EUR", "sizes": {}, "country_id": "it"}, "16077399": {"sku": "BIR34791", "lowest_price": "", "image": "", "status": "Nenurodyta FF faile", "store_id": "", "url": "", "price": "", "currency": "", "sizes": {}}, "16212297": {"sku": "BIR34793", "lowest_price": "", "image": "https://cdn-images.farfetch-contents.com/16/21/22/97/16212297_30898907_480.jpg", "status": "Konkurentu", "store_id": 9885, "url": "https://www.farfetch.com//de/shopping/women/birkenstock-milano-sandalen-item-16212297.aspx?storeid=9885", "price": 81, "currency": "EUR", "sizes": {"available": {"27": {"lastInStock": false, "storeId": 10136, "quantity": 10, "description": "41", "sizeId": 27, "variantId": "91e06d10-a952-4212-b7a0-e080c3696c8c"}, "29": {"lastInStock": false, "storeId": 9885, "quantity": 24, "description": "42", "sizeId": 29, "variantId": "bee6e56a-3d8b-4e77-a41d-f610c02d1959"}, "31": {"lastInStock": false, "storeId": 9885, "quantity": 21, "description": "43", "sizeId": 31, "variantId": "fdc147fe-f000-4159-b227-b4c1d8540fbd"}, "33": {"lastInStock": false, "storeId": 10136, "quantity": 7, "description": "44", "sizeId": 33, "variantId": "d10b28b3-1c77-4291-a891-9fec1ebdd2b3"}, "35": {"lastInStock": false, "storeId": 10136, "quantity": 11, "description": "45", "sizeId": 35, "variantId": "56a4ab31-c269-461a-a873-dea0f5f05b02"}, "37": {"lastInStock": false, "storeId": 10136, "quantity": 8, "description": "46", "sizeId": 37, "variantId": "ebcce719-438e-45e6-8db0-0108e08e8de7"}}, "scaleDescription": "Italien", "cleanScaleDescription": "Italien", "showUnisex": true, "unisexLabel": "Unisex-Artikel werden in Herrengr\u00f6\u00dfen angezeigt", "isOneSize": false, "isOnlyOneLeft": false, "scaleId": 210, "convertedScaleId": null, "friendlyScaleName": "IT", "selectedSize": null}, "country_id": "it"}, "15814800": {"sku": "BIR43853", "lowest_price": "", "image": "", "status": "Nenurodyta FF faile", "store_id": "", "url": "", "price": "", "currency": "", "sizes": {}}, "15131497": {"sku": "BIR51103M", "lowest_price": "", "image": "https://cdn-images.farfetch-contents.com/15/13/14/97/15131497_25902435_480.jpg", "status": "Aktyvus", "store_id": 11719, "url": "https://www.farfetch.com//de/shopping/men/birkenstock-arizona-sandalen-item-15131497.aspx?storeid=11719", "price": 108, "currency": "EUR", "sizes": {}, "country_id": ""}, "16096844": {"sku": "BIR51103W", "lowest_price": "", "image": "", "status": "Nenurodyta FF faile", "store_id": "", "url": "", "price": "", "currency": "", "sizes": {}}, "16078287": {"sku": "BIR51131", "lowest_price": "", "image": "", "status": "Nenurodyta FF faile", "store_id": "", "url": "", "price": "", "currency": "", "sizes": {}}, "14012117": {"sku": "BIR51151", "lowest_price": "", "image": "https://cdn-images.farfetch-contents.com/14/01/21/17/14012117_18405495_480.jpg", "status": "Aktyvus", "store_id": 10136, "url": "https://www.farfetch.com//de/shopping/men/birkenstock-arizona-sandalen-item-14012117.aspx?storeid=10136", "price": 102, "currency": "EUR", "sizes": {}, "country_id": ""}, "16210788": {"sku": "BIR51193", "lowest_price": "", "image": "https://cdn-images.farfetch-contents.com/16/21/07/88/16210788_31236454_480.jpg", "status": "Aktyvus", "store_id": 10136, "url": "https://www.farfetch.com//de/shopping/women/birkenstock-sandalen-mit-schnallenverschluss-item-16210788.aspx?storeid=10136", "price": 107, "currency": "EUR", "sizes": {}, "country_id": ""}, "14981923": {"sku": "BIR51733M", "lowest_price": "", "image": "https://cdn-images.farfetch-contents.com/14/98/19/23/14981923_25724590_480.jpg", "status": "Aktyvus", "store_id": 10136, "url": "https://www.farfetch.com//de/shopping/men/birkenstock-pantoletten-mit-schnallen-item-14981923.aspx?storeid=10136", "price": 87, "currency": "EUR", "sizes": {}, "country_id": ""}, "13885242": {"sku": "BIR51733W", "lowest_price": "", "image": "", "status": "Nenurodyta FF faile", "store_id": "", "url": "", "price": "", "currency": "", "sizes": {}}, "12892600": {"sku": "BIR51793M", "lowest_price": "", "image": "https://cdn-images.farfetch-contents.com/12/89/26/00/12892600_21365261_480.jpg", "status": "Konkurentu", "store_id": 9462, "url": "https://www.farfetch.com//de/shopping/men/birkenstock-sandalen-mit-schnallen-item-12892600.aspx?storeid=9462", "price": 64, "currency": "EUR", "sizes": {"available": {"17": {"lastInStock": false, "storeId": 9462, "quantity": 9, "description": "36", "sizeId": 17, "variantId": "d0f40000-3a26-000d-0129-08d591b09915"}, "19": {"lastInStock": false, "storeId": 11025, "quantity": 10, "description": "37", "sizeId": 19, "variantId": "d0f40000-3a26-000d-6152-08d591b09915"}, "21": {"lastInStock": false, "storeId": 11025, "quantity": 19, "description": "38", "sizeId": 21, "variantId": "d0f40000-3a26-000d-c34a-08d591b09915"}, "23": {"lastInStock": false, "storeId": 9885, "quantity": 5, "description": "39", "sizeId": 23, "variantId": "d0f40000-3a26-000d-2099-08d591b09916"}, "25": {"lastInStock": false, "storeId": 9671, "quantity": 11, "description": "40", "sizeId": 25, "variantId": "d0f40000-3a26-000d-7c5e-08d591b09916"}, "27": {"lastInStock": false, "storeId": 11719, "quantity": 33, "description": "41", "sizeId": 27, "variantId": "d0f40000-3a26-000d-d777-08d591b09916"}, "29": {"lastInStock": false, "storeId": 11719, "quantity": 63, "description": "42", "sizeId": 29, "variantId": "d0f40000-3a26-000d-359d-08d591b09917"}, "31": {"lastInStock": false, "storeId": 11719, "quantity": 29, "description": "43", "sizeId": 31, "variantId": "d0f40000-3a26-000d-92e4-08d591b09917"}, "33": {"lastInStock": false, "storeId": 12801, "quantity": 10, "description": "44", "sizeId": 33, "variantId": "d0f40000-3a26-000d-fa2d-08d591b09917"}, "35": {"lastInStock": false, "storeId": 11719, "quantity": 9, "description": "45", "sizeId": 35, "variantId": "d0f40000-3a26-000d-8d4d-08d591b09918"}, "37": {"lastInStock": false, "storeId": 11719, "quantity": 2, "description": "46", "sizeId": 37, "variantId": "d0f40000-3a26-000d-e6fd-08d591b09918"}}, "scaleDescription": "Italien", "cleanScaleDescription": "Italien", "showUnisex": false, "isOneSize": false, "isOnlyOneLeft": false, "scaleId": 210, "convertedScaleId": null, "friendlyScaleName": "IT", "selectedSize": null}, "country_id": "pl"}, "15205802": {"sku": "BIR51793W", "lowest_price": "", "image": "", "status": "Nenurodyta FF faile", "store_id": "", "url": "", "price": "", "currency": "", "sizes": {}}, "16078238": {"sku": "BIR52873", "lowest_price": "", "image": "", "status": "Nenurodyta FF faile", "store_id": "", "url": "", "price": "", "currency": "", "sizes": {}}, "16078235": {"sku": "BIR551251", "lowest_price": "", "image": "", "status": "Nenurodyta FF faile", "store_id": "", "url": "", "price": "", "currency": "", "sizes": {}}, "15239738": {"sku": "BIR952093_211", "lowest_price": "", "image": "", "status": "Nenurodyta FF faile", "store_id": "", "url": "", "price": "", "currency": "", "sizes": {}}, "16672355": {"sku": "BLY6198230-BLACK", "lowest_price": 115.54, "image": "https://cdn-images.farfetch-contents.com/16/67/23/55/16672355_32644088_480.jpg", "status": "Aktyvus", "store_id": 10136, "url": "https://www.farfetch.com//de/shopping/men/bally-klassische-schnurschuhe-item-16672355.aspx?storeid=10136", "price": 398, "currency": "EUR", "sizes": {}, "country_id": ""}, "16672356": {"sku": "BLY6198231-CHOCOLATE", "lowest_price": 115.54, "image": "https://cdn-images.farfetch-contents.com/16/67/23/56/16672356_32878672_480.jpg", "status": "Aktyvus", "store_id": 10136, "url": "https://www.farfetch.com//de/shopping/men/bally-salfano-deby-schuhe-item-16672356.aspx?storeid=10136", "price": 398, "currency": "EUR", "sizes": {}, "country_id": ""}, "16671624": {"sku": "BLY6203060-BLACK", "lowest_price": 102.28, "image": "https://cdn-images.farfetch-contents.com/16/67/16/24/16671624_32882483_480.jpg", "status": "Aktyvus", "store_id": 10136, "url": "https://www.farfetch.com//de/shopping/men/bally-micson-loafer-item-16671624.aspx?storeid=10136", "price": 353, "currency": "EUR", "sizes": {}, "country_id": ""}, "11445861": {"sku": "BLY6206925-BLACK", "lowest_price": 133.85556, "image": "https://cdn-images.farfetch-contents.com/11/44/58/61/11445861_6818105_480.jpg", "status": "Konkurentu", "store_id": 9183, "url": "https://www.farfetch.com//de/shopping/men/bally-pearce-loafer-item-11445861.aspx?storeid=9183", "price": 291, "currency": "EUR", "sizes": {"available": {"23": {"lastInStock": true, "storeId": 12638, "quantity": 1, "description": "5", "sizeId": 23, "variantId": "eec70000-3a22-000d-3975-08d35f1d54a4"}, "24": {"lastInStock": true, "storeId": 12638, "quantity": 1, "description": "5.5", "sizeId": 24, "variantId": "eec70000-3a22-000d-e3a4-08d35f1d54a5"}, "26": {"lastInStock": true, "storeId": 12638, "quantity": 1, "description": "6.5", "sizeId": 26, "variantId": "eec70000-3a22-000d-c638-08d35f1d54a8"}, "27": {"lastInStock": false, "storeId": 10136, "quantity": 2, "description": "7", "sizeId": 27, "variantId": "eec70000-3a22-000d-720c-08d35f1d54aa"}, "28": {"lastInStock": false, "storeId": 12638, "quantity": 3, "description": "7.5", "sizeId": 28, "variantId": "eec70000-3a22-000d-e421-08d35f1d54ab"}, "29": {"lastInStock": false, "storeId": 9183, "quantity": 8, "description": "8", "sizeId": 29, "variantId": "eec70000-3a22-000d-5b3d-08d35f1d54ad"}, "30": {"lastInStock": true, "storeId": 12638, "quantity": 1, "description": "8.5", "sizeId": 30, "variantId": "eec70000-3a22-000d-12d9-08d35f1d54af"}, "31": {"lastInStock": false, "storeId": 10136, "quantity": 3, "description": "9", "sizeId": 31, "variantId": "eec70000-3a22-000d-8546-08d35f1d54b0"}, "33": {"lastInStock": false, "storeId": 10136, "quantity": 2, "description": "10", "sizeId": 33, "variantId": "eec70000-3a22-000d-b114-08d35f1d54b3"}, "35": {"lastInStock": false, "storeId": 10136, "quantity": 3, "description": "11", "sizeId": 35, "variantId": "eec70000-3a22-000d-dca1-08d35f1d54b6"}, "36": {"lastInStock": true, "storeId": 10136, "quantity": 1, "description": "11.5", "sizeId": 36, "variantId": "eec70000-3a22-000d-515a-08d35f1d54b8"}, "37": {"lastInStock": true, "storeId": 10136, "quantity": 1, "description": "12", "sizeId": 37, "variantId": "eec70000-3a22-000d-ea1a-08d35f1d54b9"}}, "scaleDescription": "Vereinigtes K\u00f6nigreich", "cleanScaleDescription": "Vereinigtes K\u00f6nigreich", "showUnisex": false, "isOneSize": false, "isOnlyOneLeft": false, "scaleId": 207, "convertedScaleId": null, "friendlyScaleName": "UK", "selectedSize": null}, "country_id": "fr"}, "13541817": {"sku": "BLY6206926-BLUE", "lowest_price": 139.745, "image": "https://cdn-images.farfetch-contents.com/13/54/18/17/13541817_16089069_480.jpg", "status": "Konkurentu", "store_id": 9462, "url": "https://www.farfetch.com//de/shopping/men/bally-pearce-loafer-item-13541817.aspx?storeid=9462", "price": 280, "currency": "EUR", "sizes": {}, "country_id": "pl"}, "12962891": {"sku": "BLY6210663-BLACK", "lowest_price": 125.63733, "image": "", "status": "Neaktyvus", "store_id": "", "url": "", "price": "", "currency": "", "sizes": {}}, "16672357": {"sku": "BLY6211239-BLACK", "lowest_price": 126.66833, "image": "https://cdn-images.farfetch-contents.com/16/67/23/57/16672357_32883516_480.jpg", "status": "Aktyvus", "store_id": 10136, "url": "https://www.farfetch.com//de/shopping/men/bally-salasan-loafer-item-16672357.aspx?storeid=10136", "price": 437, "currency": "EUR", "sizes": {}, "country_id": ""}, "16673145": {"sku": "BLY6211240-CHOCOLATE", "lowest_price": 126.66813, "image": "https://cdn-images.farfetch-contents.com/16/67/31/45/16673145_32886111_480.jpg", "status": "Aktyvus", "store_id": 10136, "url": "https://www.farfetch.com//de/shopping/men/bally-salasan-loafer-item-16673145.aspx?storeid=10136", "price": 437, "currency": "EUR", "sizes": {}, "country_id": ""}, "16671625": {"sku": "BLY6211729-BLACK", "lowest_price": 115.539, "image": "https://cdn-images.farfetch-contents.com/16/67/16/25/16671625_32694010_480.jpg", "status": "Aktyvus", "store_id": 10136, "url": "https://www.farfetch.com//de/shopping/men/bally-condros-high-top-sneakers-item-16671625.aspx?storeid=10136", "price": 398, "currency": "EUR", "sizes": {}, "country_id": ""}, "16673144": {"sku": "BLY6211885-COWBOY", "lowest_price": 93.52, "image": "https://cdn-images.farfetch-contents.com/16/67/31/44/16673144_32696300_480.jpg", "status": "Aktyvus", "store_id": 10136, "url": "https://www.farfetch.com//de/shopping/men/bally-christian-loafer-item-16673144.aspx?storeid=10136", "price": 322, "currency": "EUR", "sizes": {}, "country_id": ""}, "11916154": {"sku": "BLY6212883-BLU", "lowest_price": 143.24, "image": "", "status": "Nenurodyta FF faile", "store_id": "", "url": "", "price": "", "currency": "", "sizes": {}}, "16671627": {"sku": "BLY6212990-WHITE", "lowest_price": 115.54, "image": "https://cdn-images.farfetch-contents.com/16/67/16/27/16671627_32881136_480.jpg", "status": "Aktyvus", "store_id": 10136, "url": "https://www.farfetch.com//de/shopping/men/bally-hercules-high-top-sneakers-item-16671627.aspx?storeid=10136", "price": 398, "currency": "EUR", "sizes": {}, "country_id": ""}, "16672358": {"sku": "BLY6216732-BLACK", "lowest_price": 142.05778, "image": "https://cdn-images.farfetch-contents.com/16/67/23/58/16672358_32878463_480.jpg", "status": "Aktyvus", "store_id": 10136, "url": "https://www.farfetch.com//de/shopping/men/bally-verzierte-loafer-item-16672358.aspx?storeid=10136", "price": 490, "currency": "EUR", "sizes": {}, "country_id": ""}, "16671640": {"sku": "BLY6217414-DKGREY", "lowest_price": 108.91, "image": "https://cdn-images.farfetch-contents.com/16/67/16/40/16671640_32695091_480.jpg", "status": "Aktyvus", "store_id": 10136, "url": "https://www.farfetch.com//de/shopping/men/bally-avion-sneakers-mit-einsatzen-item-16671640.aspx?storeid=10136", "price": 376, "currency": "EUR", "sizes": {}, "country_id": ""}, "16671629": {"sku": "BLY6217415-INK", "lowest_price": 108.91, "image": "https://cdn-images.farfetch-contents.com/16/67/16/29/16671629_32695124_480.jpg", "status": "Aktyvus", "store_id": 10136, "url": "https://www.farfetch.com//de/shopping/men/bally-avion-sneakers-item-16671629.aspx?storeid=10136", "price": 376, "currency": "EUR", "sizes": {}, "country_id": ""}, "16671630": {"sku": "BLY6217419-INK", "lowest_price": 108.91, "image": "https://cdn-images.farfetch-contents.com/16/67/16/30/16671630_32878823_480.jpg", "status": "Aktyvus", "store_id": 10136, "url": "https://www.farfetch.com//de/shopping/men/bally-avion-fo-sneakers-item-16671630.aspx?storeid=10136", "price": 376, "currency": "EUR", "sizes": {}, "country_id": ""}, "16673150": {"sku": "BLY6217425-IVY", "lowest_price": 143.24, "image": "https://cdn-images.farfetch-contents.com/16/67/31/50/16673150_32693342_480.jpg", "status": "Aktyvus", "store_id": 10136, "url": "https://www.farfetch.com//de/shopping/men/bally-hiking-boots-aus-wildleder-item-16673150.aspx?storeid=10136", "price": 494, "currency": "EUR", "sizes": {}, "country_id": ""}, "16673164": {"sku": "BLY6219556-BLACK", "lowest_price": 115.54, "image": "https://cdn-images.farfetch-contents.com/16/67/31/64/16673164_32879734_480.jpg", "status": "Aktyvus", "store_id": 10136, "url": "https://www.farfetch.com//de/shopping/men/bally-avion-fo-sneakers-item-16673164.aspx?storeid=10136", "price": 398, "currency": "EUR", "sizes": {}, "country_id": ""}, "16673154": {"sku": "BLY6220364-PEANUT", "lowest_price": 115.54, "image": "https://cdn-images.farfetch-contents.com/16/67/31/54/16673154_32641325_480.jpg", "status": "Aktyvus", "store_id": 10136, "url": "https://www.farfetch.com//de/shopping/men/bally-high-top-sneakers-mit-flammen-item-16673154.aspx?storeid=10136", "price": 398, "currency": "EUR", "sizes": {}, "country_id": ""}, "16673148": {"sku": "BLY6220421-BLACK", "lowest_price": 102.28, "image": "https://cdn-images.farfetch-contents.com/16/67/31/48/16673148_32878530_480.jpg", "status": "Aktyvus", "store_id": 10136, "url": "https://www.farfetch.com//de/shopping/men/bally-klassische-loafer-item-16673148.aspx?storeid=10136", "price": 353, "currency": "EUR", "sizes": {}, "country_id": ""}, "16673168": {"sku": "BLY6220430-WHITE", "lowest_price": 108.91, "image": "https://cdn-images.farfetch-contents.com/16/67/31/68/16673168_32878607_480.jpg", "status": "Aktyvus", "store_id": 10136, "url": "https://www.farfetch.com//de/shopping/men/bally-sneakers-in-colour-block-optik-item-16673168.aspx?storeid=10136", "price": 376, "currency": "EUR", "sizes": {}, "country_id": ""}, "16672365": {"sku": "BLY6221263-NATURAL", "lowest_price": 77.18364, "image": "", "status": "Nenurodyta FF faile", "store_id": "", "url": "", "price": "", "currency": "", "sizes": {}}, "16673172": {"sku": "BLY6221317-BLACK", "lowest_price": 71.5, "image": "https://cdn-images.farfetch-contents.com/16/67/31/72/16673172_32641191_480.jpg", "status": "Aktyvus", "store_id": 10136, "url": "https://www.farfetch.com//de/shopping/men/bally-stefhan-retro-high-top-sneakers-item-16673172.aspx?storeid=10136", "price": 247, "currency": "EUR", "sizes": {}, "country_id": ""}, "16673149": {"sku": "BLY6221318-NATURAL", "lowest_price": 71.5, "image": "https://cdn-images.farfetch-contents.com/16/67/31/49/16673149_32883716_480.jpg", "status": "Aktyvus", "store_id": 10136, "url": "https://www.farfetch.com//de/shopping/men/bally-stefhan-high-top-sneakers-item-16673149.aspx?storeid=10136", "price": 247, "currency": "EUR", "sizes": {}, "country_id": ""}, "16673152": {"sku": "BLY6221320-BLACK", "lowest_price": 78.059, "image": "", "status": "Nenurodyta FF faile", "store_id": "", "url": "", "price": "", "currency": "", "sizes": {}}, "16671635": {"sku": "BLY6221322-WHITE", "lowest_price": 77.18, "image": "", "status": "Nenurodyta FF faile", "store_id": "", "url": "", "price": "", "currency": "", "sizes": {}}, "16672359": {"sku": "BLY6221370-SNUFF", "lowest_price": 90.21, "image": "https://cdn-images.farfetch-contents.com/16/67/23/59/16672359_32692668_480.jpg", "status": "Aktyvus", "store_id": 10136, "url": "https://www.farfetch.com//de/shopping/men/bally-vita-parcours-sneakers-item-16672359.aspx?storeid=10136", "price": 311, "currency": "EUR", "sizes": {}, "country_id": ""}, "16672362": {"sku": "BLY6222875-VINO", "lowest_price": 91.8625, "image": "https://cdn-images.farfetch-contents.com/16/67/23/62/16672362_32886009_480.jpg", "status": "Aktyvus", "store_id": 10136, "url": "https://www.farfetch.com//de/shopping/men/bally-warno-loafer-item-16672362.aspx?storeid=10136", "price": 317, "currency": "EUR", "sizes": {}, "country_id": ""}, "16671634": {"sku": "BLY6222876-FANGO", "lowest_price": 91.86429, "image": "https://cdn-images.farfetch-contents.com/16/67/16/34/16671634_32693922_480.jpg", "status": "Aktyvus", "store_id": 10136, "url": "https://www.farfetch.com//de/shopping/men/bally-warno-loafer-item-16671634.aspx?storeid=10136", "price": 317, "currency": "EUR", "sizes": {}, "country_id": ""}, "16673155": {"sku": "BLY6222961-VINO", "lowest_price": 77.182, "image": "https://cdn-images.farfetch-contents.com/16/67/31/55/16673155_32642024_480.jpg", "status": "Aktyvus", "store_id": 10136, "url": "https://www.farfetch.com//de/shopping/men/bally-pearce-loafer-aus-wildleder-item-16673155.aspx?storeid=10136", "price": 266, "currency": "EUR", "sizes": {}, "country_id": ""}, "16671643": {"sku": "BLY6222976-CORVETTE", "lowest_price": 98.02, "image": "https://cdn-images.farfetch-contents.com/16/67/16/43/16671643_32641107_480.jpg", "status": "Aktyvus", "store_id": 10136, "url": "https://www.farfetch.com//de/shopping/men/bally-loafer-mit-streifen-item-16671643.aspx?storeid=10136", "price": 338, "currency": "EUR", "sizes": {}, "country_id": ""}, "16673162": {"sku": "BLY6222979-BROWN", "lowest_price": 115.54, "image": "https://cdn-images.farfetch-contents.com/16/67/31/62/16673162_32881340_480.jpg", "status": "Aktyvus", "store_id": 10136, "url": "https://www.farfetch.com//de/shopping/men/bally-bardony-loafer-item-16673162.aspx?storeid=10136", "price": 398, "currency": "EUR", "sizes": {}, "country_id": ""}, "16673156": {"sku": "BLY6222982-BLACK", "lowest_price": 115.54, "image": "https://cdn-images.farfetch-contents.com/16/67/31/56/16673156_32880839_480.jpg", "status": "Aktyvus", "store_id": 10136, "url": "https://www.farfetch.com//de/shopping/men/bally-bardony-loafer-item-16673156.aspx?storeid=10136", "price": 398, "currency": "EUR", "sizes": {}, "country_id": ""}, "16673157": {"sku": "BLY6223013-BLACK", "lowest_price": 102.28, "image": "https://cdn-images.farfetch-contents.com/16/67/31/57/16673157_32641242_480.jpg", "status": "Aktyvus", "store_id": 10136, "url": "https://www.farfetch.com//de/shopping/men/bally-klassische-loafer-item-16673157.aspx?storeid=10136", "price": 353, "currency": "EUR", "sizes": {}, "country_id": ""}, "16673178": {"sku": "BLY6223041-BLACK", "lowest_price": 108.91, "image": "https://cdn-images.farfetch-contents.com/16/67/31/78/16673178_32879434_480.jpg", "status": "Aktyvus", "store_id": 10136, "url": "https://www.farfetch.com//de/shopping/men/bally-cromwell-loafer-item-16673178.aspx?storeid=10136", "price": 376, "currency": "EUR", "sizes": {}, "country_id": ""}, "16673158": {"sku": "BLY6223163-BLACK", "lowest_price": 85.94333, "image": "https://cdn-images.farfetch-contents.com/16/67/31/58/16673158_32641901_480.jpg", "status": "Aktyvus", "store_id": 10136, "url": "https://www.farfetch.com//de/shopping/men/bally-herald-slip-on-sneakers-item-16673158.aspx?storeid=10136", "price": 296, "currency": "EUR", "sizes": {}, "country_id": ""}, "16673165": {"sku": "BLY6223165-WHITE", "lowest_price": 85.94, "image": "https://cdn-images.farfetch-contents.com/16/67/31/65/16673165_32880910_480.jpg", "status": "Aktyvus", "store_id": 10136, "url": "https://www.farfetch.com//de/shopping/men/bally-herald-new-sneakers-item-16673165.aspx?storeid=10136", "price": 296, "currency": "EUR", "sizes": {}, "country_id": ""}, "16671638": {"sku": "BLY6223207-WHITE", "lowest_price": 90.20714, "image": "https://cdn-images.farfetch-contents.com/16/67/16/38/16671638_32691786_480.jpg", "status": "Aktyvus", "store_id": 10136, "url": "https://www.farfetch.com//de/shopping/men/bally-vita-parcours-high-top-sneakers-item-16671638.aspx?storeid=10136", "price": 311, "currency": "EUR", "sizes": {}, "country_id": ""}, "16673159": {"sku": "BLY6223211-BLACK", "lowest_price": 77.18167, "image": "https://cdn-images.farfetch-contents.com/16/67/31/59/16673159_32879524_480.jpg", "status": "Aktyvus", "store_id": 10136, "url": "https://www.farfetch.com//de/shopping/men/bally-new-competition-sneakers-item-16673159.aspx?storeid=10136", "price": 266, "currency": "EUR", "sizes": {}, "country_id": ""}, "16671652": {"sku": "BLY6223535-BLU", "lowest_price": 77.18375, "image": "https://cdn-images.farfetch-contents.com/16/67/16/52/16671652_32882431_480.jpg", "status": "Aktyvus", "store_id": 10136, "url": "https://www.farfetch.com//de/shopping/men/bally-smitt-sneakers-item-16671652.aspx?storeid=10136", "price": 266, "currency": "EUR", "sizes": {}, "country_id": ""}, "16672361": {"sku": "BLY6223844-BLACK", "lowest_price": 77.18286, "image": "", "status": "Nenurodyta FF faile", "store_id": "", "url": "", "price": "", "currency": "", "sizes": {}}, "16671653": {"sku": "BLY6224985-TOBACCO", "lowest_price": 100.86, "image": "https://cdn-images.farfetch-contents.com/16/67/16/53/16671653_32879358_480.jpg", "status": "Aktyvus", "store_id": 10136, "url": "https://www.farfetch.com//de/shopping/men/bally-condriac-loafer-item-16671653.aspx?storeid=10136", "price": 348, "currency": "EUR", "sizes": {}, "country_id": ""}, "16671644": {"sku": "BLY6224986-BLU", "lowest_price": 100.86, "image": "https://cdn-images.farfetch-contents.com/16/67/16/44/16671644_32643052_480.jpg", "status": "Aktyvus", "store_id": 10136, "url": "https://www.farfetch.com//de/shopping/men/bally-klassische-loafer-item-16671644.aspx?storeid=10136", "price": 348, "currency": "EUR", "sizes": {}, "country_id": ""}, "16673160": {"sku": "BLY6225017-BLACK", "lowest_price": 97.31, "image": "https://cdn-images.farfetch-contents.com/16/67/31/60/16673160_33082033_480.jpg", "status": "Aktyvus", "store_id": 10136, "url": "https://www.farfetch.com//de/shopping/men/bally-orivel-sneakers-item-16673160.aspx?storeid=10136", "price": 336, "currency": "EUR", "sizes": {}, "country_id": ""}, "16671642": {"sku": "BLY6225018-BLU", "lowest_price": 97.31, "image": "https://cdn-images.farfetch-contents.com/16/67/16/42/16671642_32641653_480.jpg", "status": "Aktyvus", "store_id": 10136, "url": "https://www.farfetch.com//de/shopping/men/bally-orivel-sneakers-item-16671642.aspx?storeid=10136", "price": 336, "currency": "EUR", "sizes": {}, "country_id": ""}, "16673179": {"sku": "BLY6225029-GARNET", "lowest_price": 93.52, "image": "https://cdn-images.farfetch-contents.com/16/67/31/79/16673179_32692400_480.jpg", "status": "Aktyvus", "store_id": 10136, "url": "https://www.farfetch.com//de/shopping/men/bally-frenz-sneakers-item-16673179.aspx?storeid=10136", "price": 322, "currency": "EUR", "sizes": {}, "country_id": ""}, "16673161": {"sku": "BLY6225652-BLACK", "lowest_price": 102.28, "image": "https://cdn-images.farfetch-contents.com/16/67/31/61/16673161_32879206_480.jpg", "status": "Aktyvus", "store_id": 10136, "url": "https://www.farfetch.com//de/shopping/men/bally-klassische-loafer-item-16673161.aspx?storeid=10136", "price": 353, "currency": "EUR", "sizes": {}, "country_id": ""}, "16671646": {"sku": "BLY6225889-WHITE", "lowest_price": 84.76, "image": "", "status": "Nenurodyta FF faile", "store_id": "", "url": "", "price": "", "currency": "", "sizes": {}}, "16673163": {"sku": "BLY6225971-TERRA", "lowest_price": 104.64842, "image": "https://cdn-images.farfetch-contents.com/16/67/31/63/16673163_32879651_480.jpg", "status": "Aktyvus", "store_id": 10136, "url": "https://www.farfetch.com//de/shopping/men/bally-pievo-loafer-item-16673163.aspx?storeid=10136", "price": 361, "currency": "EUR", "sizes": {}, "country_id": ""}, "16671647": {"sku": "BLY6226035-TERRA", "lowest_price": 121.22, "image": "", "status": "Nenurodyta FF faile", "store_id": "", "url": "", "price": "", "currency": "", "sizes": {}}, "16673175": {"sku": "BLY6226047-WHITE", "lowest_price": 92.57303, "image": "", "status": "Nenurodyta FF faile", "store_id": "", "url": "", "price": "", "currency": "", "sizes": {}}, "16672364": {"sku": "BLY6226052-INK", "lowest_price": 77.184, "image": "", "status": "Nenurodyta FF faile", "store_id": "", "url": "", "price": "", "currency": "", "sizes": {}}, "16673170": {"sku": "BLY6226071-BLACK", "lowest_price": 77.18, "image": "https://cdn-images.farfetch-contents.com/16/67/31/70/16673170_32695106_480.jpg", "status": "Aktyvus", "store_id": 10136, "url": "https://www.farfetch.com//de/shopping/men/bally-smake-sneakers-item-16673170.aspx?storeid=10136", "price": 266, "currency": "EUR", "sizes": {}, "country_id": ""}, "16673180": {"sku": "BLY6226097-WHEAT", "lowest_price": 85.94333, "image": "", "status": "Nenurodyta FF faile", "store_id": "", "url": "", "price": "", "currency": "", "sizes": {}}, "16671649": {"sku": "BLY6226099-WHITE", "lowest_price": 95.90389, "image": "https://cdn-images.farfetch-contents.com/16/67/16/49/16671649_32880932_480.jpg", "status": "Aktyvus", "store_id": 10136, "url": "https://www.farfetch.com//de/shopping/men/bally-klassische-sneakers-item-16671649.aspx?storeid=10136", "price": 331, "currency": "EUR", "sizes": {}, "country_id": ""}, "16671654": {"sku": "BLY6226101-MULTICAME", "lowest_price": 95.90353, "image": "https://cdn-images.farfetch-contents.com/16/67/16/54/16671654_32878456_480.jpg", "status": "Aktyvus", "store_id": 10136, "url": "https://www.farfetch.com//de/shopping/men/bally-karierte-sneakers-item-16671654.aspx?storeid=10136", "price": 331, "currency": "EUR", "sizes": {}, "country_id": ""}, "16672367": {"sku": "BLY6228286-PRUNE", "lowest_price": 77.18375, "image": "https://cdn-images.farfetch-contents.com/16/67/23/67/16672367_32878587_480.jpg", "status": "Aktyvus", "store_id": 10136, "url": "https://www.farfetch.com//de/shopping/men/bally-pearce-loafer-item-16672367.aspx?storeid=10136", "price": 266, "currency": "EUR", "sizes": {}, "country_id": ""}, "14001249": {"sku": "BLY6228389-BLACK", "lowest_price": 63.63909, "image": "https://cdn-images.farfetch-contents.com/14/00/12/49/14001249_18175618_480.jpg", "status": "Konkurentu", "store_id": 9383, "url": "https://www.farfetch.com//de/shopping/men/bally-slaim-pantoletten-item-14001249.aspx?storeid=9383", "price": 139, "currency": "EUR", "sizes": {"available": {"25": {"lastInStock": false, "storeId": 9383, "quantity": 5, "description": "6", "sizeId": 25, "variantId": "97560000-3a2f-000d-5171-08d6b9e9232f"}, "27": {"lastInStock": false, "storeId": 9462, "quantity": 8, "description": "7", "sizeId": 27, "variantId": "97560000-3a2f-000d-2089-08d6b9e92333"}, "29": {"lastInStock": false, "storeId": 9383, "quantity": 8, "description": "8", "sizeId": 29, "variantId": "97560000-3a2f-000d-93ad-08d6b9e92336"}, "31": {"lastInStock": false, "storeId": 9462, "quantity": 9, "description": "9", "sizeId": 31, "variantId": "97560000-3a2f-000d-d4ee-08d6b9e92339"}, "33": {"lastInStock": true, "storeId": 12639, "quantity": 1, "description": "10", "sizeId": 33, "variantId": "97560000-3a2f-000d-0034-08d6b9e9233d"}, "35": {"lastInStock": false, "storeId": 10136, "quantity": 3, "description": "11", "sizeId": 35, "variantId": "97560000-3a2f-000d-4faa-08d6b9e9233f"}, "39": {"lastInStock": true, "storeId": 12639, "quantity": 1, "description": "13", "sizeId": 39, "variantId": "97560000-3a2f-000d-6ab2-08d6b9e92343"}}, "scaleDescription": "Vereinigtes K\u00f6nigreich", "cleanScaleDescription": "Vereinigtes K\u00f6nigreich", "showUnisex": false, "isOneSize": false, "isOnlyOneLeft": false, "scaleId": 207, "convertedScaleId": null, "friendlyScaleName": "UK", "selectedSize": null}, "country_id": "it"}, "16673177": {"sku": "BLY6230209-JEAN", "lowest_price": 91.86, "image": "https://cdn-images.farfetch-contents.com/16/67/31/77/16673177_32879693_480.jpg", "status": "Aktyvus", "store_id": 10136, "url": "https://www.farfetch.com//de/shopping/men/bally-waltec-loafer-item-16673177.aspx?storeid=10136", "price": 317, "currency": "EUR", "sizes": {}, "country_id": ""}, "16671656": {"sku": "BLY6230213-JEAN", "lowest_price": 91.88, "image": "https://cdn-images.farfetch-contents.com/16/67/16/56/16671656_32890064_480.jpg", "status": "Aktyvus", "store_id": 10136, "url": "https://www.farfetch.com//de/shopping/men/bally-klassische-loafer-item-16671656.aspx?storeid=10136", "price": 317, "currency": "EUR", "sizes": {}, "country_id": ""}, "16672368": {"sku": "BLY6230216-JEAN", "lowest_price": 91.88, "image": "https://cdn-images.farfetch-contents.com/16/67/23/68/16672368_32879440_480.jpg", "status": "Aktyvus", "store_id": 10136, "url": "https://www.farfetch.com//de/shopping/men/bally-warno-loafer-item-16672368.aspx?storeid=10136", "price": 317, "currency": "EUR", "sizes": {}, "country_id": ""}, "15012768": {"sku": "BLY6230663-BLACK", "lowest_price": 121.74, "image": "https://cdn-images.farfetch-contents.com/15/01/27/68/15012768_25117042_480.jpg", "status": "Aktyvus", "store_id": 10136, "url": "https://www.farfetch.com//de/shopping/men/bally-sneakers-mit-logo-item-15012768.aspx?storeid=10136", "price": 352, "currency": "EUR", "sizes": {}, "country_id": ""}, "16202850": {"sku": "BLY6231433-BLACK", "lowest_price": 141.1475, "image": "", "status": "Nenurodyta FF faile", "store_id": "", "url": "", "price": "", "currency": "", "sizes": {}}, "15368155": {"sku": "BLY6231507-BLACK", "lowest_price": 157.068, "image": "https://cdn-images.farfetch-contents.com/15/36/81/55/15368155_27014606_480.jpg", "status": "Aktyvus", "store_id": 10136, "url": "https://www.farfetch.com//de/shopping/men/bally-pantoletten-mit-streifen-item-15368155.aspx?storeid=10136", "price": 408, "currency": "EUR", "sizes": {}, "country_id": ""}, "15367924": {"sku": "BLY6231508-BLACK", "lowest_price": 141.15, "image": "https://cdn-images.farfetch-contents.com/15/36/79/24/15367924_27017265_480.jpg", "status": "Aktyvus", "store_id": 10136, "url": "https://www.farfetch.com//de/shopping/men/bally-pantoletten-mit-streifen-item-15367924.aspx?storeid=10136", "price": 327, "currency": "EUR", "sizes": {}, "country_id": ""}}